Workbook

Sheet Модель ROI
A1: ГигаЧат Бизнес — Калькулятор ROI (3 года)
A2: Адаптированная модель для российского рынка | Синий = входные данные | Чёрный = формула
A4: ▶ ВХОДНЫЕ ПАРАМЕТРЫ | D4: ▶ РЕЗУЛЬТАТЫ (3 ГОДА)
A6: Отрасль | B6: Ритейл и FMCG | D6: Чистая экономия (3 года) | E6: =B84 -> 148322000
A7: Годовая выручка | B7: 5–15 млрд руб. | D7: ROI (%) | E7: =B85 -> 868.39578
A8: Число пользователей ГигаЧат (10–500) | B8: 200 | D8: Срок окупаемости | E8: =B86 -> 3
A9: Уровень AI-зрелости | B9: Развивающийся (пилоты) | D9: Эквивалент FTE (год 3) | E9: =B87 -> 42.857143
A10: Агентский бюджет (руб./год) | B10: 3000000
A11: Размер стека инструментов | B11: Средний (4–7 инструментов)
A13: USE CASES (выбрать Да / Нет)
A14: Генерация контента | B14: Да
A15: Поддержка клиентов | B15: Да
A16: Юридические документы | B16: Да
A17: HR и онбординг | B17: Да
A18: Аналитика и отчётность | B18: Да
A19: Продажи и КП | B19: Да
D21: РАЗБИВКА ВЫГОД (3 ГОДА)
D22: Трудовые выгоды (ФОТ) | E22: =B55 -> 162000000
D23: Выгоды по агентствам | E23: =B63 -> 1575000
D24: Экономия на инструментах | E24: =B70 -> 1323000
D25: Compliance / теневой AI | E25: =B77 -> 504000
D26: Итого выгоды (3 года) | E26: =B81 -> 165402000
D27: Затраты на платформу (3 года) | E27: =B82 -> 17080000
A30: БЛОК 1 — ЗАТРАТЫ НА ГИГАЧАТ БИЗНЕС
A31: Базовая стоимость на пользователя/год, руб. | B31: =Справочники!B49 -> 28000
A32: Рассчитанная стоимость (пользователи × база), руб. | B32: =B8*B31 -> 5600000
A33: Год 1 (с надбавкой за внедрение) — мин. 2 500 000 руб. | B33: =MAX(B32*(1+Справочники!B50), Справочники!B52) -> 6440000
A34: Год 2 (базовый) | B34: =MAX(B32, Справочники!B52) -> 5600000
A35: Год 3 (скидка лояльности) | B35: =MAX(B32*(1-Справочники!B51), Справочники!B52) -> 5040000
A37: ИТОГО ЗАТРАТЫ (3 ГОДА) | B37: =B33+B34+B35 -> 17080000
A39: БЛОК 2 — ТРУДОВЫЕ ВЫГОДЫ (экономия ФОТ)
A40: Загруженный ФОТ сотрудника по отрасли, руб./год | B40: =IFERROR(INDEX(Справочники!$B$4:$B$9,MATCH($B$6,Справочники!$A$4:$A$9,0)),2000000) -> 1800000
A41: Базовых часов экономии (AI-зрелость), ч/нед/польз. | B41: =IFERROR(INDEX(Справочники!$B$13:$B$15,MATCH($B$9,Справочники!$A$13:$A$15,0)),2.5) -> 4
A42: Доп. часов от выбранных use cases, ч/нед/польз. | B42: =SUMPRODUCT((B14:B19="Да")*Справочники!$B$34:$B$39) -> 3.5
A43: Итого часов экономии, ч/нед/польз. | B43: =B41+B42 -> 7.5
A44: Рабочих часов в год (35 ч × 52 нед) | B44: 1820
A45: FTE эквивалент (полная отдача) | B45: =B8*B43*52/B44 -> 42.857143
A46: Трудовые выгоды (полная отдача), руб./год | B46: =B45*B40 -> 77142857
A47: Трудовые выгоды — Год 1 (рамп 30%) | B47: =B46*Справочники!$B$43 -> 23142857
A48: Трудовые выгоды — Год 2 (рамп 80%) | B48: =B46*Справочники!$B$44 -> 61714286
A49: Трудовые выгоды — Год 3 (рамп 100%) | B49: =B46*Справочники!$B$45 -> 77142857
A55: ИТОГО ТРУДОВЫЕ ВЫГОДЫ (3 ГОДА) | B55: =B47+B48+B49 -> 162000000
A57: БЛОК 3 — ВЫГОДЫ ОТ ЗАМЕЩЕНИЯ АГЕНТСТВ
A58: Агентский бюджет в год, руб. | B58: =B10 -> 3000000
A59: Ставка замещения по отрасли | B59: =IFERROR(INDEX(Справочники!$B$19:$B$24,MATCH($B$6,Справочники!$A$19:$A$24,0)),0.15) -> 0.25
A60: Агентские выгоды — Год 1 | B60: =B58*B59*Справочники!$B$43 -> 225000
A61: Агентские выгоды — Год 2 | B61: =B58*B59*Справочники!$B$44 -> 600000
A62: Агентские выгоды — Год 3 | B62: =B58*B59*Справочники!$B$45 -> 750000
A63: ИТОГО АГЕНТСКИЕ ВЫГОДЫ (3 ГОДА) | B63: =B60+B61+B62 -> 1575000
A65: БЛОК 4 — ЭКОНОМИЯ НА ИНСТРУМЕНТАХ (консолидация стека)
A66: Стоимость заменяемых инструментов, руб./польз./год | B66: =IFERROR(INDEX(Справочники!$B$28:$B$30,MATCH($B$11,Справочники!$A$28:$A$30,0)),7000) -> 7000
A67: Ставка консолидации инструментов | B67: =Справочники!B59 -> 0.45
A68: Выгоды от консолидации — Год 1 | B68: =B8*B66*B67*Справочники!$B$43 -> 189000
A69: Выгоды от консолидации — Год 2 | B69: =B8*B66*B67*Справочники!$B$44 -> 504000
A70: ИТОГО ВЫГОДЫ ИНСТРУМЕНТЫ (3 ГОДА) | B70: =B68+B69+B8*B66*B67*Справочники!$B$45 -> 1323000
A72: БЛОК 5 — COMPLIANCE И ТЕНЕВОЙ AI (152-ФЗ)
A73: Расход на теневой AI, руб./польз./год | B73: =Справочники!B56 -> 4200
A74: Доля сотрудников с теневым AI | B74: =Справочники!B57 -> 0.4
A75: Ставка замещения (снижение риска нарушений 152-ФЗ) | B75: =Справочники!B58 -> 0.5
A76: Годовые compliance-выгоды (теневой AI + риск) | B76: =B8*B73*B74*B75 -> 168000
A77: ИТОГО COMPLIANCE ВЫГОДЫ (3 ГОДА) | B77: =B76*3 -> 504000
A80: ИТОГОВЫЕ ПОКАЗАТЕЛИ ROI
A81: Общие выгоды (3 года), руб. | B81: =B55+B63+B70+B77 -> 165402000
A82: Общие затраты (3 года), руб. | B82: =B37 -> 17080000
A84: Чистая экономия (3 года), руб. | B84: =B81-B82 -> 148322000
A85: ROI (%) | B85: =IFERROR((B84/B82)*100,0) -> 868.39578
A86: Срок окупаемости, мес. | B86: =IFERROR(IF((B47-B33)>=0, ROUND(B33/B47*12,0), IF((B47+B48-B33-B34)>=0, 12+ROUND((B33+B34-B47)/B48*12,0), ">24")), "-") -> 3
A87: Эквивалент FTE (год 3, полная отдача) | B87: =B45 -> 42.857143
A90: ⚠ Все расчёты носят оценочный характер и не являются гарантией результата. Стоимость платформы (Таб. 7 Справочников) необходимо уточнить у менеджера ГигаЧат Бизнес. ФОТ указан с учётом страховых взносов (30.2%). Рамп-ап: год 1 — 30%, год 2 — 80%, год 3 — 100%.

Sheet Справочники
A2: Таб. 1 — Загруженный ФОТ сотрудника по отраслям (руб./год)
A3: Отрасль | B3: ФОТ загруженный, руб./год
A4: IT и технологии | B4: 2400000
A5: Финансы и страхование | B5: 2800000
A6: Ритейл и FMCG | B6: 1800000
A7: Промышленность | B7: 1600000
A8: Профессиональные услуги | B8: 2200000
A9: Телеком и медиа | B9: 2000000
A11: Таб. 2 — Экономия времени по уровню AI-зрелости (ч/нед/польз.)
A12: Уровень AI-зрелости | B12: Часов/нед/пользователь
A13: Начальный (нет опыта) | B13: 2.5
A14: Развивающийся (пилоты) | B14: 4
A15: Зрелый (AI в процессах) | B15: 6
A17: Таб. 3 — Ставка замещения агентских расходов по отраслям
A18: Отрасль | B18: Ставка замещения
A19: IT и технологии | B19: 0.2
A20: Финансы и страхование | B20: 0.15
A21: Ритейл и FMCG | B21: 0.25
A22: Промышленность | B22: 0.12
A23: Профессиональные услуги | B23: 0.15
A24: Телеком и медиа | B24: 0.2
A26: Таб. 4 — Стоимость заменяемых инструментов (руб./польз./год)
A27: Размер стека | B27: Стоимость инструментов
A28: Малый (1–3 инструмента) | B28: 3500
A29: Средний (4–7 инструментов) | B29: 7000
A30: Большой (8+ инструментов) | B30: 12000
A32: Таб. 5 — Дополнительная экономия времени по use cases (ч/нед/польз.)
A33: Use Case | B33: Доп. часов/нед/польз.
A34: Генерация контента | B34: 0.8
A35: Поддержка клиентов | B35: 0.5
A36: Юридические документы | B36: 0.6
A37: HR и онбординг | B37: 0.4
A38: Аналитика и отчётность | B38: 0.5
A39: Продажи и КП | B39: 0.7
A41: Таб. 6 — Коэффициенты внедрения (рамп-ап) по годам
A42: Год | B42: Коэф. внедрения (от полной отдачи)
A43: Год 1 | B43: 0.3
A44: Год 2 | B44: 0.8
A45: Год 3 | B45: 1
A47: Таб. 7 — Параметры ценообразования ГигаЧат Бизнес (SaaS) ⚠ уточнить
A48: Параметр | B48: Значение
A49: Базовая стоимость на польз./год, руб. | B49: 28000
A50: Надбавка год 1 (внедрение) | B50: 0.15
A51: Скидка год 3 (лояльность) | B51: 0.1
A52: Минимальная стоимость в год, руб. | B52: 2500000
A54: Таб. 8 — Параметры compliance (теневой AI)
A55: Параметр | B55: Значение
A56: Расход на теневой AI/польз./год, руб. | B56: 4200
A57: Доля сотрудников с теневым AI | B57: 0.4
A58: Ставка замещения (снижение риска) | B58: 0.5
A59: Ставка консолидации инструментов | B59: 0.45
A62: Источники: red_mad_robot 2025, HeadHunter salary data, Superjob 2025, внутренние данные
A63: ФОТ включает страховые взносы (30.2%). Часы экономии — консервативная оценка на основе OpenAI/Microsoft productivity research.
