Workbook

Sheet Методология
A1: Методология расчета экономической эффективности внедрения GenAI
A2: Основание и Стандарты Данная модель разработана на основе «Методологии оценки финансовой эффективности от ИИ/ГенИИ», утвержденной Альянсом в сфере ИИ и Ассоциацией ФинТех (АФТ). Модель адаптирована под специфику Generative AI, учитывая вероятностный характер генерации, необходимость проверки (Human-in-the-loop) и нелинейное влияние на бизнес-метрики. Ключевые принципы расчета - Принцип консерватизма: В расчетах используется разделение на прямую экономию бюджета, ненайм и рост потенциала. Защита от двойного счета: - Реализована сегрегация штата: сотрудники, учтенные в профильных департаментах (Юристы, IT), автоматически исключаются из расчета общей продуктивности. - Эффекты "Ускорения работы" и "Ненайма" не суммируются, а вкладываются друг в друга. Чистый экономический эффект: - Учитываются не только лицензии (GigaB2B), но и стоимость инфраструктуры, внедрения и налоговые отчисления. - Расчет ведется с учетом Ставки дисконтирования, приводящей будущие потоки к стоимости денег во времени.

Sheet Финансы и Стандарты
A1: Параметр | B1: Значение | C1: Комментарий
A2: Ставка дисконтирования | B2: 0.18
A3: Налог | B3: 0.25 | C3: Ставка налога на прибыль. Под вопросом. Можно не учитывать
A4: Нагрузка на ФОТ | B4: 1.4 | C4: (НДФЛ + Соцвзносы + ДМС + Офис). Обычно 1.3 - 1.4 Должно привязываться к ставке в час
A5: Годовой объем контрактуемой выручки | B5: 1000000000

Sheet Затраты
A1: Параметр | B1: Значение | C1: Комментарий
A2: Модель размещения (продукт)
A3: Цена за входящие токены
A4: Цена за генерацию
A5: Стоимость сервера | C5: Ежегодный платеж
A6: Зарплата DevOps/Admin на поддержку
A7: DAU клиента
A8: Количество параллельны запросов
A9: Количество серверов

Sheet Общая продуктивность
A1: Общая продуктивность
A2: Параметр | B2: Значение | C2: Комментарий
A3: Наименование департамента | B3: Все
A4: Роли | B4: Все
A5: Текущий штат без ИИ департаментов | B5: =B6-'ИИ Юрист'!B5 -> 2980
A6: Текущий штат | B6: 3000
A7: Оптимизация штата (ненайм)
A8: Средняя зарплата (gross) | B8: 100000
A9: На сколько планировали вырасти без ИИ | B9: 0.02
A10: На сколько планировали вырасти без ИИ FTE | B10: =B5*B9 -> 59.6
A11: Выгоды от ненайма (не считается в формуле): | B11: =((B8*'Финансы и Стандарты'!B4)*B10)*12 -> 100128000
A12: Ускорение онбординга сотрудников
A13: Текучесть кадров | B13: 0.1
A14: Срок адаптации, мес | B14: 3
A15: % ускорения | B15: 0.1
A16: Выгоды от ускорения онбординга: | B16: =((B5*B13)*(B14*B8))*B15 -> 8940000
A17: Ускорение выполнения задач
A18: Какую часть рабочего дня можно ускорить | B18: 0.2
A19: Проникнование GenAI (использование сотрудниками в рутинных задачах) | B19: 0.2
A20: Итого ускорение (в FTE) | B20: =B5*B19*B18 -> 119.2
A21: Выгоды от ускорения выполнения задач. годовай: | B21: =(B20*B8*'Финансы и Стандарты'!B4)*12 -> 2.00256e+08
A22: Общий итог: | B22: =B16+B21 -> 2.09196e+08

Sheet ИИ Юрист
A1: ИИ Юрист
A2: Параметр | B2: Значение
A3: Наименование департамента | B3: Юридический
A4: Роли | B4: Юрист
A5: Текущий штат | B5: 20
A6: Ненайм
A7: Средняя зарплата (gross) | B7: 100000
A8: На сколько планировали вырасти без ИИ | B8: 0.1
A9: На сколько планировали вырасти без ИИ | B9: =B5*B8 -> 2
A10: Выгоды от ненайма (не считается в формуле): | B10: =((B7*'Финансы и Стандарты'!B4)*B9)*12 -> 3360000
A12: Онбординг
A13: Текучесть кадров | B13: 0.1
A14: Срок адаптации | B14: 6
A15: % ускорения | B15: 0.2
A16: Выгоды от ускорения онбординга: | B16: =((B5*B13)*(B14*B7))*B15 -> 240000
A17: Ускорение выполнения задач
A18: Какую часть рабочего дня можно ускорить | B18: 0.5
A19: Ожидаемое ускорение на этих задачах | B19: 0.7
A20: Итого ускорение (в FTE) | B20: =B5*B19*B18 -> 7
A21: Выгоды от ускорения выполнения задач: | B21: =(B20*B7*'Финансы и Стандарты'!B4)*12 -> 11760000
A22: Влияние на скорость сделок
A23: Текущий цикл согласования (SLA) (дни) | B23: 10
A24: Ожидаемое ускорение цикла с ИИ | B24: 0.3
A25: Коэфф. конверсии скорости в выручку | B25: 0.005
A26: Влияние на драйвер | B26: 0.15
A27: Влияние на скорость сделок: | B27: =('Финансы и Стандарты'!B5*B24*B25)*B26 -> 225000
A28: Снижение Рисков
A29: Среднегодовой объем штрафов/исков | B29: 5000000
A30: Снижение пропущенных рисков | B30: 0.25
A31: Снижение юридических рисков: | B31: =B29*B30 -> 1250000
A32: Общий итог: | B32: =B16+B21+B27+B31 -> 13475000

Sheet ROI
B1: Год 1 | C1: Год 2 | D1: Год 3 | E1: Год 4 | F1: Год 5 | G1: TOTAL
A2: Масштабирование использования | B2: 0.3 | C2: 0.5 | D2: 0.8 | E2: 0 | F2: 0
A3: Доходная часть
A4: Выгоды Общая продуктивность | B4: =('Общая продуктивность'!$B$22*B2) -> 62758800 | C4: =('Общая продуктивность'!$B$22*C2) -> 1.04598e+08 | D4: =('Общая продуктивность'!$B$22*D2) -> 167356800 | E4: =('Общая продуктивность'!$B$22*E2) -> 0 | F4: =('Общая продуктивность'!$B$22*F2) -> 0 | G4: =SUM(B4:F4) -> 334713600
A6: 8 типовых
A8: ИИ Юрист | B8: =('ИИ Юрист'!B32*B2) -> 4042500 | C8: ='ИИ Юрист'!B32*C2 -> 6737500 | D8: ='ИИ Юрист'!B32*D2 -> 10780000 | E8: ='ИИ Юрист'!B32*E2 -> 0 | F8: ='ИИ Юрист'!B32*F2 -> 0 | G8: =SUM(B8:F8) -> 21560000
A9: Итого выгоды | B9: =B4+B8 -> 66801300 | C9: =C4+C8 -> 1.113355e+08 | D9: =D4+D8 -> 178136800 | E9: =E4+E8 -> 0 | F9: =F4+F8 -> 0 | G9: =SUM(B9:F9) -> 356273600
A11: Стоимость GigaChat | B11: =Затраты!B3+Затраты!B4+Затраты!B5+Затраты!B6 -> 0 | C11: =(Затраты!B3+Затраты!B4+Затраты!B5+Затраты!B6)/2 -> 0 | D11: =(Затраты!B3+Затраты!B4+Затраты!B5+Затраты!B6)/2 -> 0 | G11: =SUM(B11:F11) -> 0
A12: Внедрение | B12: 10000000 | C12: 0 | D12: 0 | E12: 0 | F12: 0 | G12: =SUM(B12:F12) -> 10000000
A13: Поддержка | B13: 0 | C13: 8000000 | D13: 8000000 | G13: =SUM(B13:F13) -> 16000000
A14: Общие затраты | B14: =B11+B12+B13 -> 10000000 | C14: =C11+C12+C13 -> 8000000 | D14: =D11+D12+D13 -> 8000000 | E14: =E11+E12+E13 -> 0 | F14: =F11+F12+F13 -> 0 | G14: =SUM(B14:F14) -> 26000000
A15: Операц. Доход | B15: =B9-B14 -> 56801300 | C15: =C9-C14 -> 1.033355e+08 | D15: =D9-D14 -> 170136800 | E15: =E9-E14 -> 0 | F15: =F9-F14 -> 0 | G15: =SUM(B15:F15) -> 330273600
A16: Налог | B16: =IF(B15>0,B15*'Финансы и Стандарты'!$B$3,0) -> 14200325 | C16: =IF(C15>0,C15*'Финансы и Стандарты'!$B$3,0) -> 25833875 | D16: =IF(D15>0,D15*'Финансы и Стандарты'!$B$3,0) -> 42534200 | E16: =IF(E15>0,E15*'Финансы и Стандарты'!$B$3,0) -> 0 | F16: =IF(F15>0,F15*'Финансы и Стандарты'!$B$3,0) -> 0 | G16: =SUM(B16:F16) -> 82568400
A17: После налога | B17: =B15-B16 -> 42600975 | C17: =C15-C16 -> 77501625 | D17: =D15-D16 -> 127602600 | E17: =E15-E16 -> 0 | F17: =F15-F16 -> 0 | G17: =SUM(B17:F17) -> 2.477052e+08
A18: Дисконтирование | B18: =1/(1+'Финансы и Стандарты'!$B$2)^1 -> 0.84745763 | C18: =1/(1+'Финансы и Стандарты'!$B$2)^2 -> 0.71818443 | D18: =1/(1+'Финансы и Стандарты'!$B$2)^3 -> 0.60863087 | E18: =1/(1+'Финансы и Стандарты'!$B$2)^4 -> 0.51578888 | F18: =1/(1+'Финансы и Стандарты'!$B$2)^5 -> 0.43710922
A19: NPV (чистая приведенная прибыль) | B19: =B15*B18 -> 48136695 | C19: =C15*C18 -> 74213947 | D19: =D15*D18 -> 1.0355051e+08 | E19: =E15*E18 -> 0 | F19: =F15*F18 -> 0 | G19: =SUM(B19:F19) -> 2.2590115e+08
A20: ROI | B20: =(G9-G14-G16)/(G14+G16) -> 2.2815589
B22: Год 1 | C22: Год 2 | D22: Год 3 | E22: Год 4 | F22: Год 5
A23: Выгоды | B23: =B9 -> 66801300 | C23: =C9 -> 1.113355e+08 | D23: =D9 -> 178136800 | E23: =E9 -> 0 | F23: =F9 -> 0
A24: Общие затраты | B24: =-B14 -> -10000000 | C24: =-C14 -> -8000000 | D24: =-D14 -> -8000000 | E24: =-E14 -> 0 | F24: =-F14 -> 0
A25: NPV | B25: =B19 -> 48136695 | C25: =C19 -> 74213947 | D25: =D19 -> 1.0355051e+08 | E25: =E19 -> 0 | F25: =F19 -> 0
